geoscan_core/__init__.py
geoscan_core-0.1.0.dist-info/WHEEL
geoscan_core-0.1.0.dist-info/METADATA
geoscan_core-0.1.0.dist-info/RECORD
